gcp/geocoding/GCPGeocoding.py
gcp/geocoding/GCPGeocodingResults.py
gcp/geocoding/__init__.py
gcp_alpa-0.0.9.dist-info/LICENSE
gcp_alpa-0.0.9.dist-info/METADATA
gcp_alpa-0.0.9.dist-info/WHEEL
gcp_alpa-0.0.9.dist-info/top_level.txt
gcp_alpa-0.0.9.dist-info/RECORD
