Metadata-Version: 2.1
Name: gcp-alpa
Version: 0.0.9
Summary: GCP API Wrapper
Home-page: https://github.com/alpaalpa/gcp
Author: Albert Pang
Author-email: alpaaccount@mac.com
License: UNKNOWN
Platform: UNKNOWN
Classifier: Programming Language :: Python :: 3
Classifier: License :: OSI Approved :: MIT License
Classifier: Operating System :: OS Independent
Requires-Python: >=3.8
Requires-Dist: munch
Requires-Dist: requests
